easy_tos/__init__.py
easy_tos/core.py
easy_tos/img_utils.py
easy_tos/io_utils.py
easy_tos/parallel.py
easy_tos/system_util.py
easy_tos-0.7.13.dist-info/METADATA
easy_tos-0.7.13.dist-info/WHEEL
easy_tos-0.7.13.dist-info/top_level.txt
easy_tos-0.7.13.dist-info/RECORD
