Metadata-Version: 2.4
Name: easy_tos
Version: 0.7.13
Summary: A simple wrapper for tos
Author: Jiaqi Wu
Classifier: Programming Language :: Python :: 3.9
Classifier: License :: OSI Approved :: MIT License
Requires-Dist: tos
Requires-Dist: tqdm
Requires-Dist: pillow
Requires-Dist: pandas
Dynamic: author
Dynamic: classifier
Dynamic: description
Dynamic: description-content-type
Dynamic: requires-dist
Dynamic: summary
